{
    "BLR+UKR+111":[
        [
            "20220325+../news_crawling/RUS_UKR/p_articles/dailymail.co.uk/The Putin battle plan that was doomed to fall apart The seeds of the Russian.txt+eventbasecode111+eventcode111+avgtone0.48315868263473055+goldsteinscale0.4+nummentions0.00181422351233672+numarticles0.00036258158085569254+numsources0.0+news_keywords+['crimea:0.4697', 'kremlin:0.448', 'ukrainians:0.4081', 'infantry:0.36', 'invading:0.3462', 'strategy:0.3168', 'tank:0.2672', 'proceed:0.2659', 'misbriefed:0.2521', 'zelensky:0.2461', 'table:0.2287', 'failure:0.2235', 'fight:0.2168', 'northward:0.2015', 'turn:0.1998', 'structure:0.1985', 'pronged:0.189', 'cite:0.186', 'donbas:0.1824', 'report:0.181', 'president:0.1749', 'bucha:0.1492', 'overall:0.1476', 'young:0.145', 'big:0.1393', 'bloodless:0.1384', 'fall:0.1369', 'nearly:0.1338', 'current:0.1286', 'integrate:0.1156']+titles_keywords+['putin:0.3816', 'failure:0.3654', 'plan:0.2956', 'dannatt:0.236', 'general:0.2092']"
        ]
    ],
    "GBR+RUS+111":[
        [
            "20220228+../news_crawling/RUS_UKR/p_articles/dailymail.co.uk/We will do everything we can to help Ukraine declares GlaxoSmithKline chief Emma Walmsley.txt+eventbasecode111+eventcode111+avgtone0.5074906367041199+goldsteinscale0.4+nummentions0.0021770682148040637+numarticles0.0029006526468455403+numsources0.0+news_keywords+['glaxosmithkline:0.5186', 'ukraine:0.4385', 'haleon:0.3281', 'healthcare:0.3007', 'humanitarian:0.2949', 'business:0.2832', 'ftse:0.2626', 'resolve:0.2435', 'group:0.2405', 'invasion:0.2334', 'want:0.2289', 'comply:0.2273', 'separation:0.2254', 'volatility:0.2008', 'staff:0.1951', 'brand:0.1914', 'demerger:0.1632', 'utterly:0.1547', 'cross:0.1503', 'cause:0.1488', 'big:0.1458', 'sensodyne:0.1444', 'reveal:0.1387', 'despite:0.1267', 'effort:0.1255', 'accord:0.1226', 'walmsley:0.105', 'decade:0.0992', 'plank:0.0949', 'week:0.0516']+titles_keywords+['glaxosmithkline:0.4466', 'ukraine:0.3461', 'walmsley:0.2143', 'emma:0.2135', 'chief:0.1294']"
        ]
    ],
    "GBR+UKR+111":[
        [
            "20220223+../news_crawling/RUS_UKR/p_articles/dailymail.co.uk/Half of Russians believe it is RIGHT to use military force to keep Ukraine out.txt+eventbasecode111+eventcode111+avgtone0.47890625+goldsteinscale0.4+nummentions0.001451378809869376+numarticles0.002175489485134155+numsources0.0+news_keywords+['ukrainians:0.5016', 'ukrainewas:0.4519', 'putin:0.4433', 'soviet:0.4326', 'nato:0.3912', 'separatists:0.3644', 'rostov:0.348', 'invade:0.341', 'frontlines:0.2621', 'peaceful:0.2482', 'readiness:0.2466', 'unite:0.2326', 'border:0.2246', 'scaremongering:0.2209', 'cyberattack:0.2193', 'blood:0.2176', 'reality:0.1885', 'predict:0.1809', 'historical:0.1787', 'read:0.1649', 'order:0.1631', 'truck:0.1602', 'reject:0.1357', 'population:0.1345', 'ready:0.1343', 'compare:0.1279', 'end:0.1058', 'hour:0.1047', 'highlight:0.0792', 'agree:0.0678']+titles_keywords+['russians:0.4735', 'nato:0.4327', 'half:0.2327', 'poll:0.2057', 'reuniting:0.1673']"
        ],
        [
            "20220313+../news_crawling/RUS_UKR/p_articles/dailymail.co.uk/Olga Thomas composer for the Queen tells ME MY MONEY about compensation fight I turned.txt+eventbasecode111+eventcode111+avgtone0.5125+goldsteinscale0.4+nummentions0.0+numarticles0.0007251631617113851+numsources0.0+news_keywords+['olga:0.4027', 'compose:0.3591', 'classical:0.3186', 'gulag:0.3153', 'owe:0.3135', 'accountant:0.3122', 'royalty:0.3078', 'claim:0.2878', 'bereavement:0.2841', 'british:0.2832', 'proceeds:0.2775', 'production:0.2734', 'hear:0.2447', 'kindly:0.2353', 'care:0.2334', 'continue:0.2315', 'arrange:0.2188', 'piece:0.2121', 'title:0.2105', 'th:0.2033', 'free:0.2022', 'leave:0.1979', 'voluntary:0.1978', 'record:0.1867', 'thousand:0.1831', 'appal:0.1805', 'heartbreaking:0.1589', 'elderly:0.1556', 'itcost:0.1553', 'lower:0.1138']+titles_keywords+['compensation:0.4316', 'olga:0.3328', 'composer:0.2982', 'mistake:0.2273', 'fight:0.2144']"
        ]
    ],
    "RUS+MDA+111":[
        [
            "20220502+../news_crawling/RUS_UKR/p_articles/dailymail.co.uk/Blasts rock Moldova as fears rise that Vladimir Putin could be eyeing next target for.txt+eventbasecode111+eventcode111+avgtone0.4685466377440347+goldsteinscale0.4+nummentions0.0043541364296081275+numarticles0.005076142131979695+numsources0.0+news_keywords+['moldovans:0.4987', 'putin:0.4975', 'ukraine:0.4952', 'moscow:0.4596', 'russias:0.4361', 'nato:0.4103', 'transnistria:0.3692', 'lavrov:0.3208', 'war:0.2977', 'explosion:0.2576', 'tiraspol:0.2438', 'nation:0.2365', 'report:0.2225', 'unions:0.216', 'worry:0.2074', 'cancerous:0.1931', 'predict:0.1907', 'push:0.1752', 'caused:0.1594', 'progress:0.1536', 'state:0.144', 'rise:0.1398', 'want:0.1353', 'consolidate:0.1237', 'rattle:0.1206', 'nearly:0.1152', 'radio:0.1106', 'theyre:0.0929', 'mr:0.0864', 'tiny:0.0782']+titles_keywords+['putin:0.514', 'moldova:0.4402', 'invasion:0.3026', 'rock:0.2643', 'eyeing:0.0908']"
        ]
    ],
    "RUS+RUS+111":[
        [
            "20220514+../news_crawling/RUS_UKR/p_articles/dailymail.co.uk/Coup to oust Putin is already under way Ukraines spy chief believes tyrant will be.txt+eventbasecode111+eventcode111+avgtone0.4812362030905078+goldsteinscale0.4+nummentions0.010522496371552975+numarticles0.011240029006526469+numsources0.01644736842105263+news_keywords+['putin:0.5552', 'crimean:0.4472', 'sochi:0.3622', 'predict:0.3041', 'news:0.3021', 'coup:0.2883', 'table:0.2607', 'armageddon:0.2459', 'chemotherapy:0.2411', 'federation:0.2408', 'report:0.2342', 'april:0.2146', 'affair:0.205', 'chiefgeneral:0.1998', 'turn:0.1953', 'celebrate:0.194', 'retreat:0.1785', 'sabre:0.1746', 'covid:0.1739', 'oust:0.1726', 'end:0.1711', 'appearance:0.1662', 'ready:0.1627', 'increasingly:0.1596', 'amid:0.1494', 'university:0.139', 'endocrinology:0.1362', 'right:0.1282', 'include:0.128', 'fahrenheit:0.0509']+titles_keywords+['putin:0.5508', 'oligarch:0.4379', 'coup:0.3654', 'blood:0.2408', 'oust:0.1641']"
        ]
    ],
    "RUS+UKR+111":[
        [
            "20220224+../news_crawling/RUS_UKR/p_articles/dailymail.co.uk/More than 150 senior Russian officials sign open letter condemning Putins invasion of Ukraine as.txt+eventbasecode111+eventcode111+avgtone0.4641638225255973+goldsteinscale0.4+nummentions0.06748911465892599+numarticles0.0681653372008702+numsources0.29276315789473684+news_keywords+['ukraine:0.4461', 'putins:0.3883', 'airstrike:0.3755', 'militarise:0.3734', 'invasion:0.3567', 'geopolitical:0.3199', 'herashchenko:0.2855', 'threat:0.2614', 'protesters:0.2477', 'accompany:0.2277', 'nazify:0.2233', 'catastrophic:0.2229', 'president:0.2033', 'andveliky:0.1935', 'approve:0.1912', 'order:0.1911', 'forward:0.1863', 'truck:0.1838', 'describing:0.1814', 'blame:0.177', 'signatory:0.1765', 'result:0.1735', 'morev:0.1651', 'declare:0.1634', 'showingbloodied:0.1572', 'stop:0.149', 'town:0.1438', 'hour:0.116', 'deputyanna:0.1086', 'today:0.0824']+titles_keywords+['russian:0.3315', 'warn:0.2106', 'officials:0.1923', 'atrocity:0.1908', 'open:0.1197']"
        ],
        [
            "20220509+../news_crawling/RUS_UKR/p_articles/dailymail.co.uk/The dawn of EU lite Macron invites Britain to join an alternative European political community.txt+eventbasecode111+eventcode111+avgtone0.5034562211981567+goldsteinscale0.4+nummentions0.010159651669085631+numarticles0.010877447425670777+numsources0.009868421052631578+news_keywords+['macron:0.4673', 'brexit:0.4458', 'eu:0.4031', 'treaty:0.3508', 'putin:0.3495', 'strasbourg:0.2797', 'election:0.276', 'bloc:0.2574', 'russias:0.2527', 'union:0.2499', 'organisation:0.2174', 'form:0.2123', 'come:0.2046', 'keynote:0.1677', 'vladmir:0.1651', 'oppose:0.1623', 'create:0.1616', 'left:0.1465', 'integration:0.1375', 'agreemet:0.1362', 'tomorrow:0.1359', 'coronavirus:0.1359', 'concentric:0.1194', 'measure:0.116', 'official:0.1141', 'easy:0.1056', 'mr:0.1022', 'oneandahalf:0.0997', 'decade:0.0993', 'apparently:0.0965']+titles_keywords+['brexit:0.4972', 'macron:0.4353', 'eu:0.3634', 'join:0.2072', 'years:0.1707']"
        ],
        [
            "20220718+../news_crawling/RUS_UKR/p_articles/dailymail.co.uk/HM becomes latest multinational firm to wind down its Russian business as Ukraine war rages.txt+eventbasecode111+eventcode111+avgtone0.486784140969163+goldsteinscale0.4+nummentions0.000725689404934688+numarticles0.0014503263234227702+numsources0.0+news_keywords+['ukraine:0.4712', 'multinational:0.3965', 'business:0.3853', 'stock:0.3349', 'invade:0.2898', 'investor:0.2867', 'firm:0.2736', 'sell:0.2711', 'operation:0.2706', 'fashion:0.2626', 'situation:0.2442', 'employ:0.2325', 'continue:0.2305', 'report:0.2172', 'launch:0.1788', 'current:0.1728', 'hm:0.1695', 'march:0.1657', 'saddened:0.1621', 'say:0.1582', 'rage:0.1571', 'late:0.1416', 'helmersson:0.1402', 'base:0.1389', 'impossible:0.1278', 'reopen:0.1164', 'fully:0.1136', 'helena:0.1103', 'accord:0.0845', 'careful:0.0845']+titles_keywords+['ukraine:0.3834', 'multinational:0.3755', 'hm:0.2471', 'war:0.2128', 'latest:0.096']"
        ]
    ],
    "UKR+RUS+111":[
        [
            "20220224+../news_crawling/RUS_UKR/p_articles/dailymail.co.uk/General Sir Patrick Sanders is appointed the new British Army chief during Russian invasion of.txt+eventbasecode111+eventcode111+avgtone0.49395161290322576+goldsteinscale0.4+nummentions0.008708272859216255+numarticles0.009427121102248005+numsources0.006578947368421052+news_keywords+['regimental:0.3648', 'military:0.3444', 'general:0.3182', 'appoint:0.3083', 'chief:0.3034', 'strategic:0.2652', 'adviser:0.263', 'invasion:0.2629', 'operation:0.2538', 'sanders:0.2294', 'uk:0.2227', 'russian:0.2173', 'government:0.2129', 'reinforce:0.2103', 'mr:0.203', 'forces:0.1908', 'patrickwas:0.1775', 'developingand:0.1559', 'queen:0.1481', 'unprovoked:0.1467', 'level:0.1418', 'smith:0.1383', 'current:0.1294', 'new:0.123', 'cyber:0.1176', 'confirm:0.1143', 'uncertain:0.1109', 'say:0.104', 'june:0.087', 'head:0.0851']+titles_keywords+['chief:0.3564', 'army:0.3494', 'ukraine:0.3175', 'sanders:0.2913', 'wont:0.138']"
        ],
        [
            "20220315+../news_crawling/RUS_UKR/p_articles/dailymail.co.uk/Britain must grown its own food and produce more crops to protect itself from shortage.txt+eventbasecode111+eventcode111+avgtone0.46910112359550565+goldsteinscale0.4+nummentions0.0+numarticles0.0007251631617113851+numsources0.0+news_keywords+['ukraine:0.3843', 'produce:0.3692', 'grow:0.3175', 'barley:0.3029', 'crop:0.2674', 'food:0.2658', 'shortage:0.2544', 'tory:0.2512', 'invasion:0.2143', 'ensure:0.2073', 'conflict:0.1998', 'feed:0.1995', 'chicken:0.1991', 'warn:0.1736', 'cause:0.1513', 'population:0.1466', 'stock:0.1367', 'rise:0.1349', 'insulate:0.1283', 'importance:0.1097', 'george:0.1054', 'leading:0.1051', 'brings:0.1002', 'potentially:0.091', 'world:0.0776', 'secretary:0.0714', 'kawczynski:0.0699', 'summer:0.0697', 'price:0.0661', 'big:0.0586']+titles_keywords+['produce:0.4252', 'russias:0.3225', 'tory:0.3176', 'protect:0.1929', 'price:0.0647']",
            "20220318+../news_crawling/RUS_UKR/p_articles/dailymail.co.uk/Race against time to save up to 1300 Ukrainians including children trapped under ruins of.txt+eventbasecode111+eventcode111+avgtone0.4479638009049775+goldsteinscale0.4+nummentions0.0+numarticles0.0007251631617113851+numsources0.0+news_keywords+['crimea:0.5013', 'kremlin:0.4497', 'ukrainians:0.445', 'genocide:0.4345', 'evacuees:0.4003', 'airstrikes:0.3847', 'propaganda:0.3768', 'humanitarian:0.3466', 'survive:0.3094', 'crisis:0.308', 'bombedout:0.2907', 'battlefield:0.2853', 'destroy:0.2806', 'capital:0.2533', 'underway:0.2531', 'zelensky:0.2348', 'know:0.2233', 'march:0.2146', 'alignment:0.2112', 'bleaker:0.2051', 'write:0.2005', 'feared:0.1918', 'th:0.1853', 'data:0.1789', 'hundreds:0.1775', 'poignant:0.1645', 'housetohouse:0.1463', 'increase:0.1413', 'far:0.1382', 'gfm:0.122']+titles_keywords+['ukrainians:0.423', 'trapped:0.2901', 'fight:0.2473', 'warns:0.1972', 'mayor:0.1954']"
        ]
    ]
}