{
    "BEL+UKR+51":[
        [
            "20220720+../news_crawling/RUS_UKR/p_articles/interfax.com/Zelensky Michel discuss 7th package of antiRussian sanctions Ukraines financial needs.txt+eventbasecode51+eventcode51+avgtone0.5023255813953488+goldsteinscale0.67+nummentions0.0021770682148040637+numarticles0.0029006526468455403+numsources0.0+news_keywords+['ukraine:0.4855', 'zelensky:0.389', 'anticorruption:0.3289', 'macroeconomic:0.3257', 'sanction:0.3239', 'euro:0.3213', 'antirussian:0.2544', 'michel:0.2436', 'commission:0.2041', 'volodymyr:0.2004', 'candidate:0.1865', 'council:0.1811', 'report:0.1803', 'cite:0.1779', 'soon:0.1751', 'dialogue:0.1606', 'package:0.1527', 'head:0.1502', 'mfa:0.1493', 'implement:0.1423', 'th:0.141', 'praise:0.1263', 'stability:0.1255', 'select:0.1162', 'discus:0.1095', 'thank:0.0954', 'year:0.0932', 'fact:0.0883', 'interfax:0.0752', 'hoped:0.0655']+titles_keywords+['sanctions:0.4924', 'zelensky:0.4742', 'ukraines:0.4129', 'financial:0.2808', 'michel:0.2489']"
        ]
    ],
    "EUR+UKR+51":[
        [
            "20220531+../news_crawling/RUS_UKR/p_articles/interfax.com/Ukraines EU candidate country status should be endorsed in June Zelensky.txt+eventbasecode51+eventcode51+avgtone0.5176056338028169+goldsteinscale0.67+nummentions0.013788098693759071+numarticles0.014503263234227702+numsources0.013157894736842105+news_keywords+['ukraine:0.5388', 'ukraines:0.4841', 'eu:0.3494', 'zelensky:0.2789', 'candidate:0.2544', 'status:0.2524', 'volodymyr:0.2011', 'june:0.1631', 'union:0.1531', 'questionnaire:0.122', 'strategic:0.1141', 'endorse:0.1096', 'membership:0.1084', 'soon:0.1049', 'fulfil:0.0965', 'count:0.0911', 'link:0.0857', 'outlet:0.0775', 'commission:0.0752', 'alternative:0.0667', 'receive:0.0646', 'complete:0.0639', 'cast:0.054', 'criterion:0.0436', 'aside:0.0422', 'necessary:0.0408', 'speech:0.0198', 'say:0.0153', 'medium:-0.0155', 'interfax:-0.0516']+titles_keywords+['ukraines:0.5065', 'zelensky:0.4062', 'candidate:0.2249', 'status:0.2204', 'june:0.2025']"
        ]
    ],
    "FRA+RUS+51":[
        [
            "20220616+../news_crawling/RUS_UKR/p_articles/interfax.com/Macron pledges support to Kyiv in confrontation with Russia.txt+eventbasecode51+eventcode51+avgtone0.5041666666666668+goldsteinscale0.67+nummentions0.0+numarticles0.0007251631617113851+numsources0.0+news_keywords+['ukraine:0.4479', 'ukrainians:0.3927', 'macron:0.3583', 'zelensky:0.222', 'french:0.1917', 'confrontation:0.1877', 'emmanuel:0.1643', 'pledge:0.1505', 'president:0.1441', 'action:0.1337', 'volodymyr:0.1292', 'thursday:0.1193', 'posture:0.113', 'resist:0.1114', 'support:0.1063', 'long:0.1041', 'continue:0.0982', 'difference:0.0922', 'visit:0.0871', 'win:0.0843', 'according:0.0779', 'unwavering:0.0754', 'quote:0.0698', 'irpin:0.057', 'say:0.044', 'term:0.0421', 'channel:0.0152', 'add:-0.0009', 'definitely:-0.0194', 'interfax:-0.0289']+titles_keywords+['kyiv:0.4642', 'macron:0.4114', 'pledges:0.186', 'confrontation:0.174', 'support:0.1142']"
        ]
    ],
    "RUS+RUS+51":[
        [
            "20220310+../news_crawling/RUS_UKR/p_articles/interfax.com/Russians aid for Donbas refugees says they support their authorities Putin.txt+eventbasecode51+eventcode51+avgtone0.5133689839572192+goldsteinscale0.67+nummentions0.0047169811320754715+numarticles0.005438723712835388+numsources0.019736842105263157+news_keywords+['refugees:0.5317', 'putin:0.5099', 'russian:0.4557', 'moscow:0.4081', 'vladimir:0.4048', 'aid:0.2899', 'support:0.2188', 'donbas:0.2175', 'citizen:0.1964', 'authority:0.1732', 'ordinary:0.1637', 'fact:0.1617', 'issue:0.1489', 'sympathy:0.1474', 'leave:0.1456', 'action:0.133', 'tell:0.1155', 'address:0.1146', 'rat:0.1133', 'grow:0.1052', 'live:0.1007', 'year:0.0901', 'thursday:0.0899', 'basement:0.0776', 'long:0.0753', 'way:0.0753', 'like:0.0609', 'sent:0.0557', 'really:0.0548', 'interfax:0.0141']+titles_keywords+['russians:0.4892', 'putin:0.4877', 'refugees:0.4773', 'donbas:0.3498', 'support:0.2202']"
        ]
    ],
    "UKR+WST+51":[
        [
            "20220303+../news_crawling/RUS_UKR/p_articles/interfax.com/Solution to Ukraine situation will be found Lavrov.txt+eventbasecode51+eventcode51+avgtone0.49029126213592233+goldsteinscale0.67+nummentions0.001451378809869376+numarticles0.002175489485134155+numsources0.0+news_keywords+['ukraine:0.5022', 'nato:0.4334', 'lavrov:0.3808', 'federation:0.2723', 'negotiation:0.2608', 'briefing:0.2589', 'solution:0.2195', 'regime:0.2062', 'attack:0.2012', 'security:0.1723', 'direct:0.16', 'document:0.1462', 'obligation:0.137', 'strengthen:0.1282', 'term:0.1246', 'continue:0.1199', 'pose:0.1135', 'thursday:0.106', 'minister:0.1029', 'aware:0.0996', 'join:0.0981', 'gomel:0.0963', 'longer:0.093', 'current:0.092', 'minimal:0.0834', 'say:0.0783', 'unquenchable:0.0708', 'particular:0.0318', 'adopt:0.0118', 'total:0.0041']+titles_keywords+['lavrov:0.5634', 'ukraine:0.451', 'solution:0.3624', 'situation:0.1822']"
        ]
    ]
}